portion/__init__.py
portion/__main__.py
portion/base/__init__.py
portion/base/command.py
portion/commands/__init__.py
portion/commands/new.py
portion/commands/template.py
portion/core/__init__.py
portion/core/logger.py
portion/core/parser.py
portion/core/project_manager.py
portion/core/template_manager.py
portion/portion.py
pyportion-0.0.6.dist-info/METADATA
pyportion-0.0.6.dist-info/WHEEL
pyportion-0.0.6.dist-info/entry_points.txt
pyportion-0.0.6.dist-info/licenses/LICENSE
pyportion-0.0.6.dist-info/RECORD
