Metadata-Version: 2.4
Name: pyportion
Version: 0.0.6
Summary: A Python CLI tool that helps developers kickstart new projects and manage existing ones
License: MIT
License-File: LICENSE
Author: Murtada
Author-email: murtada.altarouti@gmail.com
Requires-Python: >=3.10
Classifier: License :: OSI Approved :: MIT License
Classifier: Programming Language :: Python :: 3
Classifier: Programming Language :: Python :: 3.10
Classifier: Programming Language :: Python :: 3.11
Classifier: Programming Language :: Python :: 3.12
Classifier: Programming Language :: Python :: 3.13
Classifier: Programming Language :: Python :: 3.14
Requires-Dist: gitpython (==3.1.45)
Requires-Dist: platformdirs (==4.4.0)
Requires-Dist: tabulate (==0.9.0)
